CHANGES.md
LICENSE
MANIFEST.in
README.md
setup.py
apns2/__init__.py
apns2/client.py
apns2/client_test.py
apns2/notification.py
apns2/response.py
apns2_client.egg-info/PKG-INFO
apns2_client.egg-info/SOURCES.txt
apns2_client.egg-info/dependency_links.txt
apns2_client.egg-info/requires.txt
apns2_client.egg-info/top_level.txt