Metadata-Version: 1.1
Name: apns2-client
Version: 0.5.4
Summary: apns2-client is a python package designed for simple, flexible and fast Apple Push Notifications on iOS, OSX and Safari using the new HTTP/2 Push provider API.
Home-page: https://github.com/oeegor/apns2-client
Author: Egor Orlov
Author-email: oeegor@gmail.com
License: MIT License
Platform: any
Classifier: Intended Audience :: Developers
Classifier: License :: OSI Approved :: MIT License
Classifier: Operating System :: OS Independent
Classifier: Programming Language :: Python
Classifier: Programming Language :: Python :: 3.5
Classifier: Topic :: Internet :: WWW/HTTP
Classifier: Topic :: Internet :: WWW/HTTP :: Dynamic Content
